sqlalchemy_aurora_data_api/__init__.py
sqlalchemy_aurora_data_api-0.5.0.dist-info/LICENSE
sqlalchemy_aurora_data_api-0.5.0.dist-info/METADATA
sqlalchemy_aurora_data_api-0.5.0.dist-info/WHEEL
sqlalchemy_aurora_data_api-0.5.0.dist-info/entry_points.txt
sqlalchemy_aurora_data_api-0.5.0.dist-info/top_level.txt
sqlalchemy_aurora_data_api-0.5.0.dist-info/RECORD
