Metadata-Version: 2.1
Name: sqlalchemy-aurora-data-api
Version: 0.5.0
Summary: An AWS Aurora Serverless Data API dialect for SQLAlchemy
Home-page: https://github.com/chanzuckerberg/sqlalchemy-aurora-data-api
Author: Andrey Kislyuk
Author-email: kislyuk@gmail.com
License: Apache Software License
Platform: MacOS X
Platform: Posix
Classifier: Intended Audience :: Developers
Classifier: License :: OSI Approved :: Apache Software License
Classifier: Operating System :: MacOS :: MacOS X
Classifier: Operating System :: POSIX
Classifier: Programming Language :: Python
Classifier: Programming Language :: Python :: 3.8
Classifier: Programming Language :: Python :: 3.9
Classifier: Programming Language :: Python :: 3.10
Classifier: Programming Language :: Python :: 3.11
Classifier: Programming Language :: Python :: 3.12
Classifier: Topic :: Software Development :: Libraries :: Python Modules
License-File: LICENSE
Requires-Dist: sqlalchemy
Requires-Dist: aurora-data-api>=0.5.0
